LICENSE
MANIFEST.in
pyproject.toml
setup.py
src/pyvectra/__init__.py
src/pyvectra/pyvectra.py
src/pyvectra/tensor_ops.cp314-win_amd64.pyd
src/pyvectra.egg-info/PKG-INFO
src/pyvectra.egg-info/SOURCES.txt
src/pyvectra.egg-info/dependency_links.txt
src/pyvectra.egg-info/top_level.txt