Metadata-Version: 2.4
Name: pyvectra
Version: 0.1.0
Summary: A tiny tensor library for self learning
Author-email: falcontreatred <eagledefalcon13@gmail.com>
License-Expression: GPL-3.0-only
Project-URL: Homepage, https://github.com/KallXfalcon/vectra
Classifier: Programming Language :: Python :: 3
Classifier: Programming Language :: Python :: 3.8
Requires-Python: >=3.8
License-File: LICENSE
Dynamic: license-file
